sshtuntap/__init__.py
sshtuntap/client.py
sshtuntap/console.py
sshtuntap/linux.py
sshtuntap/network.py
sshtuntap/server.py
sshtuntap-2.0.7.dist-info/LICENSE
sshtuntap-2.0.7.dist-info/METADATA
sshtuntap-2.0.7.dist-info/WHEEL
sshtuntap-2.0.7.dist-info/entry_points.txt
sshtuntap-2.0.7.dist-info/top_level.txt
sshtuntap-2.0.7.dist-info/RECORD
