Metadata-Version: 2.1
Name: sshtuntap
Version: 2.0.7
Summary: Linux tuntap using openssh
Home-page: http://github.com/pylover/sshtuntap
Author: Vahid Mardani
Author-email: vahid.mardani@gmail.com
License: MIT
Classifier: Environment :: Console
Classifier: Intended Audience :: Developers
Classifier: Natural Language :: English
Classifier: Development Status :: 5 - Production/Stable
Classifier: License :: Other/Proprietary License
Classifier: Operating System :: POSIX :: Linux
Classifier: Programming Language :: Python :: 3.6
Classifier: Programming Language :: Python :: 3.7
License-File: LICENSE
Requires-Dist: netifaces
Requires-Dist: easycli
Requires-Dist: pymlconf (<3,>=2)
